test/__init__.py
test/biog_ind/__init__.py
test/biog_ind/biographic_index.py
test/dedup/__init__.py
test/dedup/biographic_dedup.py
test/infer/__init__.py
test/infer/biographic_inference.py
just_testing-0.1.0.dist-info/METADATA
just_testing-0.1.0.dist-info/WHEEL
just_testing-0.1.0.dist-info/top_level.txt
just_testing-0.1.0.dist-info/RECORD
