Metadata-Version: 2.4
Name: just_testing
Version: 0.1.0
Summary: Your package description
Home-page: https://github.com/yourusername/test
Author: Your Name
Author-email: Your Name <your.email@example.com>
Requires-Python: >=3.6
Requires-Dist: numpy>=1.21.0
Requires-Dist: pandas>=1.3.0
Provides-Extra: dev
Requires-Dist: pytest; extra == "dev"
Requires-Dist: black; extra == "dev"
Dynamic: author
Dynamic: home-page
Dynamic: requires-python
